datasciencelab7/__init__.py
datasciencelab7/pro1.py
datasciencelab7/pro2.py
datasciencelab7/pro3.py
datasciencelab7/pro4.py
datasciencelab7/pro5.py
datasciencelab7/pro6.py
datasciencelab7/pro7.py
datasciencelab7/pro8.py
datasciencelab7-1.2.0.dist-info/METADATA
datasciencelab7-1.2.0.dist-info/WHEEL
datasciencelab7-1.2.0.dist-info/top_level.txt
datasciencelab7-1.2.0.dist-info/RECORD
