Metadata-Version: 2.4
Name: datasciencelab7
Version: 1.2.0
Summary: Data Science Lab 7 Programs
Author: Rayan
Dynamic: author
Dynamic: summary
